evoluzo/__init__.py
evoluzo/dna.py
evoluzo/population.py
evoluzo-0.0.2.dist-info/METADATA
evoluzo-0.0.2.dist-info/WHEEL
evoluzo-0.0.2.dist-info/top_level.txt
evoluzo-0.0.2.dist-info/RECORD
