Metadata-Version: 2.1
Name: evoluzo
Version: 0.0.2
Summary: A genetic algorithm implementation
Home-page: https://github.com/pypa/sampleproject
Author: Zmee
Author-email: mail.of.zmee@gmail.com
Classifier: Programming Language :: Python :: 3
Classifier: License :: OSI Approved :: MIT License
Classifier: Operating System :: OS Independent
Requires-Python: >=3.8
